{"SURVIVAL":{"enderChestContents":{},"inventoryContents":{"19":{"==":"org.bukkit.inventory.ItemStack","type":"DOUBLE_PLANT","damage":4,"amount":27},"35":{"==":"org.bukkit.inventory.ItemStack","type":"QUARTZ_BLOCK"},"33":{"==":"org.bukkit.inventory.ItemStack","type":"GOLD_BLOCK"},"15":{"==":"org.bukkit.inventory.ItemStack","type":"POTION","damage":16418},"34":{"==":"org.bukkit.inventory.ItemStack","type":"LOG_2"},"13":{"==":"org.bukkit.inventory.ItemStack","type":"SKULL_ITEM","damage":2},"14":{"==":"org.bukkit.inventory.ItemStack","type":"TORCH"},"11":{"==":"org.bukkit.inventory.ItemStack","type":"DOUBLE_PLANT","damage":1,"amount":39},"12":{"==":"org.bukkit.inventory.ItemStack","type":"DIRT","amount":9},"21":{"==":"org.bukkit.inventory.ItemStack","type":"LEAVES"},"20":{"==":"org.bukkit.inventory.ItemStack","type":"LOG"},"22":{"==":"org.bukkit.inventory.ItemStack","type":"WOOD_DOOR"},"23":{"==":"org.bukkit.inventory.ItemStack","type":"DIAMOND_BLOCK"},"24":{"==":"org.bukkit.inventory.ItemStack","type":"STEP","damage":5},"25":{"==":"org.bukkit.inventory.ItemStack","type":"STEP"},"26":{"==":"org.bukkit.inventory.ItemStack","type":"GRASS"},"27":{"==":"org.bukkit.inventory.ItemStack","type":"POTION","damage":16450},"28":{"==":"org.bukkit.inventory.ItemStack","type":"FENCE"},"29":{"==":"org.bukkit.inventory.ItemStack","type":"MONSTER_EGG","damage":65},"3":{"==":"org.bukkit.inventory.ItemStack","type":"BEACON"},"2":{"==":"org.bukkit.inventory.ItemStack","type":"SIGN"},"10":{"==":"org.bukkit.inventory.ItemStack","type":"GRILLED_PORK","amount":33},"1":{"==":"org.bukkit.inventory.ItemStack","type":"MOB_SPAWNER","amount":120},"0":{"==":"org.bukkit.inventory.ItemStack","type":"DIAMOND_SWORD","damage":12,"meta":{"==":"ItemMeta","meta-type":"UNSPECIFIC","enchants":{"FIRE_ASPECT":2,"DAMAGE_ALL":3,"KNOCKBACK":2}}},"30":{"==":"org.bukkit.inventory.ItemStack","type":"DOUBLE_PLANT","damage":2},"7":{"==":"org.bukkit.inventory.ItemStack","type":"WOOD_AXE"},"6":{"==":"org.bukkit.inventory.ItemStack","type":"WOOL","damage":15},"32":{"==":"org.bukkit.inventory.ItemStack","type":"COBBLESTONE_STAIRS"},"5":{"==":"org.bukkit.inventory.ItemStack","type":"GRAVEL"},"31":{"==":"org.bukkit.inventory.ItemStack","type":"LEAVES","damage":1},"4":{"==":"org.bukkit.inventory.ItemStack","type":"GLOWSTONE"},"9":{"==":"org.bukkit.inventory.ItemStack","type":"COOKED_BEEF","amount":6},"8":{"==":"org.bukkit.inventory.ItemStack","type":"WOOD_PICKAXE"}},"armorContents":{"2":{"==":"org.bukkit.inventory.ItemStack","type":"GOLD_CHESTPLATE","meta":{"==":"ItemMeta","meta-type":"UNSPECIFIC","enchants":{"PROTECTION_ENVIRONMENTAL":4,"THORNS":2}}},"1":{"==":"org.bukkit.inventory.ItemStack","type":"GOLD_LEGGINGS","meta":{"==":"ItemMeta","meta-type":"UNSPECIFIC","enchants":{"PROTECTION_ENVIRONMENTAL":3}}},"0":{"==":"org.bukkit.inventory.ItemStack","type":"GOLD_BOOTS","meta":{"==":"ItemMeta","meta-type":"UNSPECIFIC","enchants":{"PROTECTION_ENVIRONMENTAL":4,"DURABILITY":3}}}},"potions":"[{\"pd\":19078,\"pa\":10,\"pt\":1},{\"pd\":19108,\"pa\":10,\"pt\":8}]","stats":{"ra":"300","ex":"2.5669446","hp":"20","fl":"17","txp":"571","el":"25","ma":"300","sa":"0.0","xp":"0.2340424","ft":"-20","fd":"0.0"}}}